{"RPT":{"ScanTime":"0.00 sec.","ScanFile":"20180628_examconcepts_35461ca4efba37cb9234180628140206_scan.json","Warnings":0,"Success":6},"SRV":{"PHP":{"websrv":true,"openbase":true,"maxtime":true,"mysqli":true,"version":true,"ALL":"Good"},"WP":{"version":true,"core":true,"cache":true,"ismu":false,"ALL":"Good"}},"ARC":{"Size":"0B","DirCount":"0","FileCount":"0","FullCount":"0","FilterDirsAll":["\/Applications\/XAMPP\/xamppfiles\/htdocs\/demowebsite\/wp-content\/ai1wm-backups","\/Applications\/XAMPP\/xamppfiles\/htdocs\/demowebsite\/wp-content\/backups-dup-pro","\/Applications\/XAMPP\/xamppfiles\/htdocs\/demowebsite\/wp-content\/backupwordpress","\/Applications\/XAMPP\/xamppfiles\/htdocs\/demowebsite\/wp-content\/content\/cache","\/Applications\/XAMPP\/xamppfiles\/htdocs\/demowebsite\/wp-content\/contents\/cache","\/Applications\/XAMPP\/xamppfiles\/htdocs\/demowebsite\/wp-content\/infinitewp\/backups","\/Applications\/XAMPP\/xamppfiles\/htdocs\/demowebsite\/wp-content\/managewp\/backups","\/Applications\/XAMPP\/xamppfiles\/htdocs\/demowebsite\/wp-content\/old-cache","\/Applications\/XAMPP\/xamppfiles\/htdocs\/demowebsite\/wp-content\/plugins\/all-in-one-wp-migration\/storage","\/Applications\/XAMPP\/xamppfiles\/htdocs\/demowebsite\/wp-content\/updraft","\/Applications\/XAMPP\/xamppfiles\/htdocs\/demowebsite\/wp-content\/uploads\/aiowps_backups","\/Applications\/XAMPP\/xamppfiles\/htdocs\/demowebsite\/wp-content\/uploads\/backupbuddy_backups","\/Applications\/XAMPP\/xamppfiles\/htdocs\/demowebsite\/wp-content\/uploads\/backupbuddy_temp","\/Applications\/XAMPP\/xamppfiles\/htdocs\/demowebsite\/wp-content\/uploads\/ithemes-security\/backups","\/Applications\/XAMPP\/xamppfiles\/htdocs\/demowebsite\/wp-content\/uploads\/mainwp\/backup","\/Applications\/XAMPP\/xamppfiles\/htdocs\/demowebsite\/wp-content\/uploads\/pb_backupbuddy","\/Applications\/XAMPP\/xamppfiles\/htdocs\/demowebsite\/wp-content\/uploads\/snapshots","\/Applications\/XAMPP\/xamppfiles\/htdocs\/demowebsite\/wp-content\/uploads\/sucuri","\/Applications\/XAMPP\/xamppfiles\/htdocs\/demowebsite\/wp-content\/uploads\/wp-clone","\/Applications\/XAMPP\/xamppfiles\/htdocs\/demowebsite\/wp-content\/uploads\/wp_all_backup","\/Applications\/XAMPP\/xamppfiles\/htdocs\/demowebsite\/wp-content\/uploads\/wpbackitup_backups","\/Applications\/XAMPP\/xamppfiles\/htdocs\/demowebsite\/wp-content\/wfcache","\/Applications\/XAMPP\/xamppfiles\/htdocs\/demowebsite\/wp-content\/wishlist-backup","\/Applications\/XAMPP\/xamppfiles\/htdocs\/demowebsite\/wp-snapshots"],"FilterFilesAll":["\/Applications\/XAMPP\/xamppfiles\/htdocs\/demowebsite\/wp-content\/uploads\/Tree-Diagram.mp4"],"FilterExtsAll":[],"FilterInfo":{"Dirs":{"Warning":[],"Unreadable":[],"Core":["\/Applications\/XAMPP\/xamppfiles\/htdocs\/demowebsite\/wp-snapshots","\/Applications\/XAMPP\/xamppfiles\/htdocs\/demowebsite\/wp-content\/backups-dup-pro","\/Applications\/XAMPP\/xamppfiles\/htdocs\/demowebsite\/wp-content\/ai1wm-backups","\/Applications\/XAMPP\/xamppfiles\/htdocs\/demowebsite\/wp-content\/backupwordpress","\/Applications\/XAMPP\/xamppfiles\/htdocs\/demowebsite\/wp-content\/content\/cache","\/Applications\/XAMPP\/xamppfiles\/htdocs\/demowebsite\/wp-content\/contents\/cache","\/Applications\/XAMPP\/xamppfiles\/htdocs\/demowebsite\/wp-content\/infinitewp\/backups","\/Applications\/XAMPP\/xamppfiles\/htdocs\/demowebsite\/wp-content\/managewp\/backups","\/Applications\/XAMPP\/xamppfiles\/htdocs\/demowebsite\/wp-content\/old-cache","\/Applications\/XAMPP\/xamppfiles\/htdocs\/demowebsite\/wp-content\/plugins\/all-in-one-wp-migration\/storage","\/Applications\/XAMPP\/xamppfiles\/htdocs\/demowebsite\/wp-content\/updraft","\/Applications\/XAMPP\/xamppfiles\/htdocs\/demowebsite\/wp-content\/wishlist-backup","\/Applications\/XAMPP\/xamppfiles\/htdocs\/demowebsite\/wp-content\/wfcache","\/Applications\/XAMPP\/xamppfiles\/htdocs\/demowebsite\/wp-content\/uploads\/aiowps_backups","\/Applications\/XAMPP\/xamppfiles\/htdocs\/demowebsite\/wp-content\/uploads\/backupbuddy_temp","\/Applications\/XAMPP\/xamppfiles\/htdocs\/demowebsite\/wp-content\/uploads\/backupbuddy_backups","\/Applications\/XAMPP\/xamppfiles\/htdocs\/demowebsite\/wp-content\/uploads\/ithemes-security\/backups","\/Applications\/XAMPP\/xamppfiles\/htdocs\/demowebsite\/wp-content\/uploads\/mainwp\/backup","\/Applications\/XAMPP\/xamppfiles\/htdocs\/demowebsite\/wp-content\/uploads\/pb_backupbuddy","\/Applications\/XAMPP\/xamppfiles\/htdocs\/demowebsite\/wp-content\/uploads\/snapshots","\/Applications\/XAMPP\/xamppfiles\/htdocs\/demowebsite\/wp-content\/uploads\/sucuri","\/Applications\/XAMPP\/xamppfiles\/htdocs\/demowebsite\/wp-content\/uploads\/wp-clone","\/Applications\/XAMPP\/xamppfiles\/htdocs\/demowebsite\/wp-content\/uploads\/wp_all_backup","\/Applications\/XAMPP\/xamppfiles\/htdocs\/demowebsite\/wp-content\/uploads\/wpbackitup_backups"],"Instance":[]},"Files":{"Size":[],"Warning":[],"Unreadable":[],"Core":[],"Instance":["\/Applications\/XAMPP\/xamppfiles\/htdocs\/demowebsite\/wp-content\/uploads\/Tree-Diagram.mp4"]},"Exts":{"Core":[],"Instance":[]},"UDirCount":0,"UFileCount":0,"UExtCount":0,"TreeSize":[],"TreeWarning":[]},"RecursiveLinks":[],"UnreadableItems":[],"Status":{"Size":"Good","Names":"Good","UnreadableItems":"Good","AddonSites":"Good"},"Dirs":[],"Files":[]},"DB":{"Status":{"Success":true,"DB_Case":"Good","DB_Rows":"Good","DB_Size":"Good","TBL_Case":"Good","TBL_Rows":"Good","TBL_Size":"Good"},"Size":"2.53MB","Rows":"1,729","TableCount":14,"TableList":{"wp_brizy_logs":{"Case":0,"Rows":"0","Size":"16KB","USize":16384},"wp_commentmeta":{"Case":0,"Rows":"0","Size":"48KB","USize":49152},"wp_comments":{"Case":0,"Rows":"0","Size":"96KB","USize":98304},"wp_duplicator_packages":{"Case":0,"Rows":"4","Size":"64KB","USize":65536},"wp_links":{"Case":0,"Rows":"0","Size":"32KB","USize":32768},"wp_options":{"Case":0,"Rows":"235","Size":"1.09MB","USize":1146880},"wp_postmeta":{"Case":0,"Rows":"1,154","Size":"528KB","USize":540672},"wp_posts":{"Case":0,"Rows":"240","Size":"400KB","USize":409600},"wp_term_relationships":{"Case":0,"Rows":"51","Size":"32KB","USize":32768},"wp_term_taxonomy":{"Case":0,"Rows":"9","Size":"48KB","USize":49152},"wp_termmeta":{"Case":0,"Rows":"0","Size":"48KB","USize":49152},"wp_terms":{"Case":0,"Rows":"9","Size":"48KB","USize":49152},"wp_usermeta":{"Case":0,"Rows":"27","Size":"48KB","USize":49152},"wp_users":{"Case":0,"Rows":"0","Size":"64KB","USize":65536}}}}